{"nodes": [{"id": "c_xampp_htdocs_wms_fenix_src_models_zona_php", "label": "Zona.php", "file_type": "code", "source_file": "src/Models/Zona.php", "source_location": "L1"}, {"id": "c_xampp_htdocs_wms_fenix_src_models_zona_zona", "label": "Zona", "file_type": "code", "source_file": "src/Models/Zona.php", "source_location": "L8", "_callable": true}, {"id": "basemodel", "label": "BaseModel", "file_type": "code", "source_file": "", "source_location": ""}, {"id": "tenantscoped", "label": "TenantScoped", "file_type": "code", "source_file": "", "source_location": ""}, {"id": "c_xampp_htdocs_wms_fenix_src_models_zona_zona_empresa", "label": ".empresa()", "file_type": "code", "source_file": "src/Models/Zona.php", "source_location": "L17", "_callable": true}, {"id": "c_xampp_htdocs_wms_fenix_src_models_zona_zona_ubicaciones", "label": ".ubicaciones()", "file_type": "code", "source_file": "src/Models/Zona.php", "source_location": "L22", "_callable": true}, {"id": "c_xampp_htdocs_wms_fenix_src_models_zona_zona_getbyempresa", "label": ".getByEmpresa()", "file_type": "code", "source_file": "src/Models/Zona.php", "source_location": "L30", "_callable": true}], "edges": [{"source": "c_xampp_htdocs_wms_fenix_src_models_zona_php", "target": "model", "relation": "imports", "context": "import", "confidence": "EXTRACTED", "source_file": "src/Models/Zona.php", "source_location": "L5", "weight": 1.0}, {"source": "c_xampp_htdocs_wms_fenix_src_models_zona_php", "target": "tenantscoped", "relation": "imports", "context": "import", "confidence": "EXTRACTED", "source_file": "src/Models/Zona.php", "source_location": "L6", "weight": 1.0}, {"source": "c_xampp_htdocs_wms_fenix_src_models_zona_php", "target": "c_xampp_htdocs_wms_fenix_src_models_zona_zona", "relation": "contains", "confidence": "EXTRACTED", "source_file": "src/Models/Zona.php", "source_location": "L8", "weight": 1.0}, {"source": "c_xampp_htdocs_wms_fenix_src_models_zona_zona", "target": "basemodel", "relation": "inherits", "confidence": "EXTRACTED", "source_file": "src/Models/Zona.php", "source_location": "L8", "weight": 1.0}, {"source": "c_xampp_htdocs_wms_fenix_src_models_zona_zona", "target": "tenantscoped", "relation": "mixes_in", "confidence": "EXTRACTED", "source_file": "src/Models/Zona.php", "source_location": "L10", "weight": 1.0}, {"source": "c_xampp_htdocs_wms_fenix_src_models_zona_zona", "target": "c_xampp_htdocs_wms_fenix_src_models_zona_zona_empresa", "relation": "method", "confidence": "EXTRACTED", "source_file": "src/Models/Zona.php", "source_location": "L17", "weight": 1.0}, {"source": "c_xampp_htdocs_wms_fenix_src_models_zona_zona", "target": "c_xampp_htdocs_wms_fenix_src_models_zona_zona_ubicaciones", "relation": "method", "confidence": "EXTRACTED", "source_file": "src/Models/Zona.php", "source_location": "L22", "weight": 1.0}, {"source": "c_xampp_htdocs_wms_fenix_src_models_zona_zona", "target": "c_xampp_htdocs_wms_fenix_src_models_zona_zona_getbyempresa", "relation": "method", "confidence": "EXTRACTED", "source_file": "src/Models/Zona.php", "source_location": "L30", "weight": 1.0}], "raw_calls": [{"caller_nid": "c_xampp_htdocs_wms_fenix_src_models_zona_zona_empresa", "callee": "belongsTo", "is_member_call": true, "source_file": "src/Models/Zona.php", "source_location": "L19", "receiver": null}, {"caller_nid": "c_xampp_htdocs_wms_fenix_src_models_zona_zona_ubicaciones", "callee": "hasMany", "is_member_call": true, "source_file": "src/Models/Zona.php", "source_location": "L24", "receiver": null}, {"caller_nid": "c_xampp_htdocs_wms_fenix_src_models_zona_zona_getbyempresa", "callee": "get", "is_member_call": true, "source_file": "src/Models/Zona.php", "source_location": "L32", "receiver": null}, {"caller_nid": "c_xampp_htdocs_wms_fenix_src_models_zona_zona_getbyempresa", "callee": "orderBy", "is_member_call": true, "source_file": "src/Models/Zona.php", "source_location": "L32", "receiver": null}, {"caller_nid": "c_xampp_htdocs_wms_fenix_src_models_zona_zona_getbyempresa", "callee": "self", "is_member_call": false, "source_file": "src/Models/Zona.php", "source_location": "L32", "receiver": null}]}