{"nodes": [{"id": "docs_superpowers_specs_2026_05_17_tv_dashboard_360_design", "label": "TV Dashboard 360 Design Doc", "file_type": "document", "source_file": "docs/superpowers/specs/2026-05-17-tv-dashboard-360-design.md", "source_location": null, "source_url": null, "captured_at": null, "author": null, "contributor": null}], "edges": [{"source": "docs_superpowers_specs_2026_05_17_tv_dashboard_360_design", "target": "public_tv_picking", "relation": "references", "confidence": "EXTRACTED", "confidence_score": 0.95, "source_file": "docs/superpowers/specs/2026-05-17-tv-dashboard-360-design.md", "source_location": null, "weight": 1.0}, {"source": "public_tv_picking_init", "target": "public_tv_picking_refresh", "relation": "calls", "confidence": "EXTRACTED", "confidence_score": 0.9, "source_file": "docs/superpowers/specs/2026-05-17-tv-dashboard-360-design.md", "source_location": null, "weight": 1.0}, {"source": "public_tv_picking_refresh", "target": "public_tv_picking_loadpicking", "relation": "calls", "confidence": "EXTRACTED", "confidence_score": 0.9, "source_file": "docs/superpowers/specs/2026-05-17-tv-dashboard-360-design.md", "source_location": null, "weight": 1.0}, {"source": "public_tv_picking_loadpicking", "target": "public_tv_picking_renderkpis", "relation": "calls", "confidence": "EXTRACTED", "confidence_score": 0.9, "source_file": "docs/superpowers/specs/2026-05-17-tv-dashboard-360-design.md", "source_location": null, "weight": 1.0}, {"source": "public_tv_picking_loadpicking", "target": "public_tv_picking_renderplanillastable", "relation": "calls", "confidence": "EXTRACTED", "confidence_score": 0.9, "source_file": "docs/superpowers/specs/2026-05-17-tv-dashboard-360-design.md", "source_location": null, "weight": 1.0}, {"source": "public_tv_picking_loadpicking", "target": "public_tv_picking_rendercharts", "relation": "calls", "confidence": "EXTRACTED", "confidence_score": 0.9, "source_file": "docs/superpowers/specs/2026-05-17-tv-dashboard-360-design.md", "source_location": null, "weight": 1.0}, {"source": "public_tv_picking_loadpicking", "target": "public_tv_picking_renderalertas", "relation": "calls", "confidence": "EXTRACTED", "confidence_score": 0.9, "source_file": "docs/superpowers/specs/2026-05-17-tv-dashboard-360-design.md", "source_location": null, "weight": 1.0}, {"source": "public_tv_picking_startcountdown", "target": "public_tv_picking_refresh", "relation": "calls", "confidence": "EXTRACTED", "confidence_score": 0.9, "source_file": "docs/superpowers/specs/2026-05-17-tv-dashboard-360-design.md", "source_location": null, "weight": 1.0}], "hyperedges": [{"id": "tv_dashboard_refresh_cycle", "label": "TV Dashboard Refresh Cycle", "nodes": ["public_tv_picking_refresh", "public_tv_picking_loadpicking", "public_tv_picking_renderkpis", "public_tv_picking_renderplanillastable", "public_tv_picking_rendercharts", "public_tv_picking_renderalertas"], "relation": "participate_in", "confidence": "EXTRACTED", "confidence_score": 0.85, "source_file": "docs/superpowers/specs/2026-05-17-tv-dashboard-360-design.md"}]}