{"nodes": [{"id": "docs_propuesta_comercial", "label": "WMS F\u00e9nix Propuesta Comercial", "file_type": "document", "source_file": "docs/propuesta_comercial.html", "source_location": null, "source_url": null, "captured_at": null, "author": null, "contributor": null}, {"id": "docs_propuesta_comercial_agente_fenix", "label": "Agente F\u00e9nix AI Assistant (concept)", "file_type": "concept", "source_file": "docs/propuesta_comercial.html", "source_location": null, "source_url": null, "captured_at": null, "author": null, "contributor": null}, {"id": "concept_wms_fenix", "label": "WMS F\u00e9nix Product", "file_type": "concept", "source_file": "docs/propuesta_comercial.html", "source_location": null, "source_url": null, "captured_at": null, "author": null, "contributor": null}], "edges": [{"source": "docs_propuesta_comercial", "target": "concept_wms_fenix", "relation": "conceptually_related_to", "confidence": "INFERRED", "confidence_score": 0.8, "source_file": "docs/propuesta_comercial.html", "source_location": null, "weight": 0.8}, {"source": "docs_propuesta_comercial_agente_fenix", "target": "concept_wms_fenix", "relation": "conceptually_related_to", "confidence": "INFERRED", "confidence_score": 0.75, "source_file": "docs/propuesta_comercial.html", "source_location": null, "weight": 0.7}, {"source": "docs_propuesta_comercial", "target": "docs_propuesta_comercial_agente_fenix", "relation": "references", "confidence": "EXTRACTED", "confidence_score": 0.7, "source_file": "docs/propuesta_comercial.html", "source_location": null, "weight": 0.7}], "hyperedges": []}